[
  {
    "id": 25,
    "date": "08/02/2023",
    "institution": "Alior Bank",
    "account": "Konto Osobiste",
    "merchant": "ZTM Bydgoszcz",
    "amount": 6.50,
    "type": "debit",
    "categoryId": 101,
    "category": "Transport Publiczny",
    "isPending": true,
    "isTransfer": false,
    "isExpense": true,
    "isEdited": false
  },
  {
    "id": 24,
    "date": "08/02/2023",
    "institution": "Alior Bank",
    "account": "Konto Osobiste",
    "merchant": "McDonald's",
    "amount": 38.99,
    "type": "debit",
    "categoryId": 502,
    "category": "Restauracje",
    "isPending": false,
    "isTransfer": false,
    "isExpense": true,
    "isEdited": false
  },
  {
    "id": 23,
    "date": "08/02/2023",
    "institution": "Alior Bank",
    "account": "Konto Oszczędnosciowe",
    "merchant": "Pensja",
    "amount": 8500.00,
    "type": "credit",
    "categoryId": 701,
    "category": "Przelew przychodzący",
    "isPending": false,
    "isTransfer": false,
    "isExpense": false,
    "isEdited": false
  },
  {
    "id": 22,
    "date": "28/01/2023",
    "institution": "Alior Bank",
    "account": "Konto Osobiste",
    "merchant": "Koszt prowadzenia konta",
    "amount": 14.95,
    "type": "debit",
    "categoryId": 402,
    "category": "Opłaty bankowe",
    "isPending": false,
    "isTransfer": false,
    "isExpense": true,
    "isEdited": false
  },
  {
    "id": 21,
    "date": "27/01/2023",
    "institution": "Alior Bank",
    "account": "Konto Osobiste",
    "merchant": "Uber.com",
    "amount": 26.43,
    "type": "debit",
    "categoryId": 102,
    "category": "Taxi",
    "isPending": false,
    "isTransfer": false,
    "isExpense": true,
    "isEdited": false
  },
  {
    "id": 20,
    "date": "27/01/2023",
    "institution": "Alior Bank",
    "account": "Konto Osobiste",
    "merchant": "Limit odnawialny karty kredytowej",
    "amount": 1000.00,
    "type": "credit",
    "categoryId": 901,
    "category": "Limit odnawialny",
    "isPending": false,
    "isTransfer": true,
    "isExpense": false,
    "isEdited": false
  },
  {
    "id": 19,
    "date": "27/01/2023",
    "institution": "Alior Bank",
    "account": "Konto Oszczędnosciowe",
    "merchant": "ENEA",
    "amount": 382.64,
    "type": "debit",
    "categoryId": 101,
    "category": "Rachunki",
    "isPending": false,
    "isTransfer": false,
    "isExpense": true,
    "isEdited": false
  },
  {
    "id": 18,
    "date": "26/01/2023",
    "institution": "Alior Bank",
    "account": "Konto Osobiste",
    "merchant": "Play S.A.",
    "amount": 90.00,
    "type": "debit",
    "categoryId": 201,
    "category": "Usługi telekomunikacyjne",
    "isPending": false,
    "isTransfer": false,
    "isExpense": true,
    "isEdited": false
  },
  {
    "id": 17,
    "date": "26/01/2023",
    "institution": "Alior Bank",
    "account": "Konto Osobiste",
    "merchant": "Amazon",
    "amount": 145.69,
    "type": "debit",
    "categoryId": 602,
    "category": "Zakupy internetowe",
    "isPending": false,
    "isTransfer": false,
    "isExpense": true,
    "isEdited": false
  },
  {
    "id": 16,
    "date": "26/01/2023",
    "institution": "Alior Bank",
    "account": "Konto Oszczędnosciowe",
    "merchant": "Czynsz",
    "amount": 1800.00,
    "type": "debit",
    "categoryId": 601,
    "category": "Czynsz",
    "isPending": false,
    "isTransfer": false,
    "isExpense": true,
    "isEdited": false
  },
  {
    "id": 15,
    "date": "25/01/2023",
    "institution": "Alior Bank",
    "account": "Konto Oszczędnosciowe",
    "merchant": "Carrefour",
    "amount": 135.28,
    "type": "debit",
    "categoryId": 501,
    "category": "Zakupy spożywcze",
    "isPending": false,
    "isTransfer": false,
    "isExpense": true,
    "isEdited": false
  },
  {
    "id": 14,
    "date": "25/01/2023",
    "institution": "Alior Bank",
    "account": "Konto Oszczędnosciowe",
    "merchant": "Premia kwartalna",
    "amount": 2000.00,
    "type": "credit",
    "categoryId": 701,
    "category": "Przelew przychodzący",
    "isPending": false,
    "isTransfer": false,
    "isExpense": false,
    "isEdited": false
  },
  {
    "id": 13,
    "date": "25/01/2023",
    "institution": "Alior Bank",
    "account": "Konto Oszczędnosciowe",
    "merchant": "Odsetki od lokaty",
    "amount": 7.95,
    "type": "debit",
    "categoryId": 401,
    "category": "Opłaty bankowe",
    "isPending": false,
    "isTransfer": false,
    "isExpense": true,
    "isEdited": false
  },
  {
    "id": 12,
    "date": "24/01/2023",
    "institution": "Alior Bank",
    "account": "Konto Osobiste",
    "merchant": "Uber.com",
    "amount": 11.60,
    "type": "debit",
    "categoryId": 102,
    "category": "Taxi",
    "isPending": false,
    "isTransfer": false,
    "isExpense": true,
    "isEdited": false
  },
  {
    "id": 11,
    "date": "24/01/2023",
    "institution": "Alior Bank",
    "account": "Konto Osobiste",
    "merchant": "Apple",
    "amount": 19.90,
    "type": "debit",
    "categoryId": 801,
    "category": "Oprogramowanie",
    "isPending": false,
    "isTransfer": false,
    "isExpense": true,
    "isEdited": false
  },
  {
    "id": 10,
    "date": "23/01/2023",
    "institution": "Alior Bank",
    "account": "Konto Osobiste",
    "merchant": "Canal+",
    "amount": 25.00,
    "type": "debit",
    "categoryId": 301,
    "category": "Subskrypcje",
    "isPending": false,
    "isTransfer": false,
    "isExpense": true,
    "isEdited": false
  },
  {
    "id": 9,
    "date": "23/01/2023",
    "institution": "Alior Bank",
    "account": "Konto Osobiste",
    "merchant": "Biedronka",
    "amount": 50.46,
    "type": "debit",
    "categoryId": 501,
    "category": "Zakupy spożywcze",
    "isPending": false,
    "isTransfer": false,
    "isExpense": true,
    "isEdited": false
  },
  {
    "id": 8,
    "date": "23/01/2023",
    "institution": "Alior Bank",
    "account": "Konto Osobiste",
    "merchant": "Odsetki za kartę kredytowa",
    "amount": 76.23,
    "type": "credit",
    "categoryId": 402,
    "category": "Opłaty bankowe",
    "isPending": false,
    "isTransfer": false,
    "isExpense": true,
    "isEdited": false
  },
  {
    "id": 7,
    "date": "20/01/2023",
    "institution": "Alior Bank",
    "account": "Konto Oszczędnosciowe",
    "merchant": "Alior Bank",
    "amount": 150.00,
    "type": "credit",
    "categoryId": 701,
    "category": "Przelew przychodzący",
    "isPending": false,
    "isTransfer": false,
    "isExpense": false,
    "isEdited": false
  },
  {
    "id": 6,
    "date": "20/01/2023",
    "institution": "Alior Bank",
    "account": "Konto Osobiste",
    "merchant": "Media Expert",
    "amount": 1200.00,
    "type": "debit",
    "categoryId": 901,
    "category": "Zakupy internetowe",
    "isPending": false,
    "isTransfer": false,
    "isExpense": true,
    "isEdited": false
  },
  {
    "id": 5,
    "date": "20/01/2023",
    "institution": "Alior Bank",
    "account": "Konto Osobiste",
    "merchant": "BNP Paribas",
    "amount": 495.00,
    "type": "debit",
    "categoryId": 901,
    "category": "Przelew wychodzący",
    "isPending": false,
    "isTransfer": true,
    "isExpense": false,
    "isEdited": false
  },
  {
    "id": 4,
    "date": "19/01/2023",
    "institution": "Alior Bank",
    "account": "Konto Osobiste",
    "merchant": "Sony",
    "amount": 49.90,
    "type": "debit",
    "categoryId": 201,
    "category": "Subskrypcje",
    "isPending": false,
    "isTransfer": false,
    "isExpense": true,
    "isEdited": false
  },
  {
    "id": 3,
    "date": "19/01/2023",
    "institution": "Alior Bank",
    "account": "Konto Osobiste",
    "merchant": "Apple",
    "amount": 24.99,
    "type": "debit",
    "categoryId": 801,
    "category": "Oprogramowanie",
    "isPending": false,
    "isTransfer": false,
    "isExpense": true,
    "isEdited": false
  },
  {
    "id": 2,
    "date": "19/01/2023",
    "institution": "Alior Bank",
    "account": "Konto Osobiste",
    "merchant": "Uber Eats",
    "amount": 59.96,
    "type": "debit",
    "categoryId": 502,
    "category": "Restauracje",
    "isPending": false,
    "isTransfer": false,
    "isExpense": true,
    "isEdited": false
  },
  {
    "id": 1,
    "date": "15/01/2023",
    "institution": "Alior Bank",
    "account": "Konto Oszczędnosciowe",
    "merchant": "Spółdzielnia mieszkaniowa",
    "amount": 150.00,
    "type": "debit",
    "categoryId": 601,
    "category": "Czynsz",
    "isPending": false,
    "isTransfer": false,
    "isExpense": true,
    "isEdited": false
  }
 ]